jiraissueopener/__init__.py
jiraissueopener/jiraissueopener.py
robotframework_jiraissueopener-0.2.0.dist-info/METADATA
robotframework_jiraissueopener-0.2.0.dist-info/WHEEL
robotframework_jiraissueopener-0.2.0.dist-info/top_level.txt
robotframework_jiraissueopener-0.2.0.dist-info/RECORD
